kitsu/__init__.py
kitsu/client.py
kitsu/errors.py
kitsu/models.py
kitsu_wrapper-1.0.0.dist-info/LICENSE
kitsu_wrapper-1.0.0.dist-info/METADATA
kitsu_wrapper-1.0.0.dist-info/WHEEL
kitsu_wrapper-1.0.0.dist-info/top_level.txt
kitsu_wrapper-1.0.0.dist-info/RECORD
