Metadata-Version: 2.1
Name: kitsu-wrapper
Version: 1.0.0
Summary: A simple python async wrapper for the Kitsu.io API.
Home-page: https://github.com/DiscoMusic/kitsu-wrapper
Author: Naegin
Author-email: UNKNOWN
License: MIT License
Keywords: anime,manga,search,kitsu,api,wrapper
Platform: UNKNOWN
Classifier: Intended Audience :: Developers
Classifier: License :: OSI Approved :: MIT License
Classifier: Natural Language :: English
Classifier: Programming Language :: Python :: 3.6
Classifier: Programming Language :: Python :: 3.7
Classifier: Programming Language :: Python :: 3.8
Classifier: Topic :: Internet
Classifier: Topic :: Utilities
Classifier: Topic :: Software Development :: Libraries
Classifier: Topic :: Software Development :: Libraries :: Python Modules
Requires-Dist: aiohttp (<3.7.0,>=3.6.0)
